pattern/__init__.py
pattern/helpers.py
pattern/metrics.py
pattern/db/__init__.py
pattern/text/__init__.py
pattern/text/search.py
pattern/text/tree.py
pattern/text/de/__init__.py
pattern/text/de/__main__.py
pattern/text/de/de-context.txt
pattern/text/de/de-frequency.txt
pattern/text/de/de-lexicon.txt
pattern/text/de/de-morphology.txt
pattern/text/de/de-spelling.txt
pattern/text/de/de-verbs.txt
pattern/text/de/inflect.py
pattern/text/en/__init__.py
pattern/text/en/__main__.py
pattern/text/en/en-context.txt
pattern/text/en/en-entities.txt
pattern/text/en/en-frequency.txt
pattern/text/en/en-lexicon.txt
pattern/text/en/en-model.slp
pattern/text/en/en-morphology.txt
pattern/text/en/en-sentiment.xml
pattern/text/en/en-spelling.txt
pattern/text/en/en-verbs.txt
pattern/text/en/inflect.py
pattern/text/en/inflect_quantify.py
pattern/text/en/modality.py
pattern/text/en/wordlist/__init__.py
pattern/text/en/wordlist/academic.txt
pattern/text/en/wordlist/basic.txt
pattern/text/en/wordlist/profanity.txt
pattern/text/en/wordlist/stopwords.txt
pattern/text/en/wordlist/time.txt
pattern/text/en/wordnet/__init__.py
pattern/text/en/wordnet/resnik-ic2.txt
pattern/text/en/wordnet/resnik-ic3.txt
pattern/text/en/wordnet/dict/LICENSE.txt
pattern/text/en/wordnet/dict/data.adj
pattern/text/en/wordnet/dict/data.adv
pattern/text/en/wordnet/dict/data.noun1
pattern/text/en/wordnet/dict/data.noun2
pattern/text/en/wordnet/dict/data.verb
pattern/text/en/wordnet/dict/index.32
pattern/text/en/wordnet/dict/index.adj
pattern/text/en/wordnet/dict/index.adv
pattern/text/en/wordnet/dict/index.noun
pattern/text/en/wordnet/dict/index.sense
pattern/text/en/wordnet/dict/index.verb
pattern/text/en/wordnet/dict/lexnames
pattern/text/es/__init__.py
pattern/text/es/__main__.py
pattern/text/es/es-context.txt
pattern/text/es/es-frequency.txt
pattern/text/es/es-lexicon.txt
pattern/text/es/es-morphology.txt
pattern/text/es/es-spelling.txt
pattern/text/es/es-verbs.txt
pattern/text/es/inflect.py
PatternLite-3.6.dist-info/LICENSE.txt
PatternLite-3.6.dist-info/METADATA
PatternLite-3.6.dist-info/WHEEL
PatternLite-3.6.dist-info/top_level.txt
PatternLite-3.6.dist-info/RECORD
